fin_choices_utils
orm_choices
